spin_phonon_suite/__init__.py
spin_phonon_suite/__version__.py
spin_phonon_suite/cli.py
spin_phonon_suite/derivative.py
spin_phonon_suite/experiments.py
spin_phonon_suite/lvc.py
spin_phonon_suite/polarisation_derivatives.py
spin_phonon_suite/vibrations.py
spin_phonon_suite-1.13.1.dist-info/licenses/LICENSE
spin_phonon_suite-1.13.1.dist-info/METADATA
spin_phonon_suite-1.13.1.dist-info/WHEEL
spin_phonon_suite-1.13.1.dist-info/entry_points.txt
spin_phonon_suite-1.13.1.dist-info/top_level.txt
spin_phonon_suite-1.13.1.dist-info/RECORD
