Metadata-Version: 2.4
Name: spin_phonon_suite
Version: 1.13.1
Summary: A package for performing spin-phonon coupling calculations with openMOLCAS, VASP, and Gaussian
Home-page: https://gitlab.com/chilton-group/spin_phonon_suite
Author: Chilton Group
Author-email: nicholas.chilton@manchester.ac.uk
Project-URL: Bug Tracker, https://gitlab.com/chilton-group/spin_phonon_suite/-/issues
Project-URL: Documentation, https://chilton-group.gitlab.io/spin_phonon_suite
Classifier: Programming Language :: Python :: 3
Classifier: License :: OSI Approved :: GNU General Public License v3 (GPLv3)
Classifier: Operating System :: OS Independent
Requires-Python: >=3.9
License-File: LICENSE
Requires-Dist: numpy<2.0.0
Requires-Dist: scipy
Requires-Dist: h5py
Requires-Dist: xyz_py>=5.1.0
Requires-Dist: angmom_suite>=1.22.0
Requires-Dist: hpc_suite>=1.8.0
Requires-Dist: matplotlib
Requires-Dist: gaussian_suite>=1.11.0
Requires-Dist: phonopy==2.22.0
Requires-Dist: molvis>=0.3.0
Requires-Dist: molcas_suite>=1.21.0
Requires-Dist: ase
Requires-Dist: env_suite
Requires-Dist: vasp_suite>=1.9.0
Requires-Dist: spglib==2.0.2
Dynamic: author
Dynamic: author-email
Dynamic: classifier
Dynamic: description
Dynamic: description-content-type
Dynamic: home-page
Dynamic: license-file
Dynamic: project-url
Dynamic: requires-dist
Dynamic: requires-python
Dynamic: summary
